[
  {
    "id": 1,
    "name": "Sahara Desert",
    "location": "North Africa",
    "area_sq_km": 9100000,
    "description": "The largest hot desert in the world, known for its vast sand dunes, oases, and extreme climate.",
    "best_time_to_visit": "October to April",
    "activities": ["Camel Safari", "Sandboarding", "Stargazing"],
    "image": "/images/deserts/sahara.jpg"
  },
  {
    "id": 2,
    "name": "Thar Desert",
    "location": "India / Pakistan",
    "area_sq_km": 200000,
    "description": "Known as the Great Indian Desert, famous for its cultural heritage, sand dunes, and camel rides.",
    "best_time_to_visit": "November to February",
    "activities": ["Camel Rides", "Desert Camping", "Cultural Shows"],
    "image": "/images/deserts/thar.jpg"
  },
  {
    "id": 3,
    "name": "Gobi Desert",
    "location": "China / Mongolia",
    "area_sq_km": 1295000,
    "description": "A cold desert known for its unique landscapes, dinosaur fossils, and nomadic culture.",
    "best_time_to_visit": "May to September",
    "activities": ["Wildlife Viewing", "Photography", "Trekking"],
    "image": "/images/deserts/gobi.jpg"
  },
  {
    "id": 4,
    "name": "Kalahari Desert",
    "location": "Botswana / Namibia / South Africa",
    "area_sq_km": 900000,
    "description": "A semi-arid sandy savanna known for its wildlife and the indigenous San people.",
    "best_time_to_visit": "May to September",
    "activities": ["Wildlife Safari", "Photography", "Cultural Tours"],
    "image": "/images/deserts/kalahari.jpg"
  },
  {
    "id": 5,
    "name": "Atacama Desert",
    "location": "Chile",
    "area_sq_km": 105000,
    "description": "The driest desert in the world, known for its salt flats, geysers, and otherworldly landscapes.",
    "best_time_to_visit": "March to May & September to November",
    "activities": ["Stargazing", "Hiking", "Photography"],
    "image": "/images/deserts/atacama.jpg"
  },
  {
    "id": 6,
    "name": "Mojave Desert",
    "location": "USA",
    "area_sq_km": 124000,
    "description": "Home to the famous Death Valley and Joshua Tree National Park, known for its extreme heat and unique vegetation.",
    "best_time_to_visit": "October to April",
    "activities": ["Hiking", "Photography", "Camping"],
    "image": "/images/deserts/mojave.jpg"
  }
]
